doapfiend_ebuild.py
setup.py
doapfiend_ebuild.egg-info/PKG-INFO
doapfiend_ebuild.egg-info/SOURCES.txt
doapfiend_ebuild.egg-info/dependency_links.txt
doapfiend_ebuild.egg-info/entry_points.txt
doapfiend_ebuild.egg-info/requires.txt
doapfiend_ebuild.egg-info/top_level.txt