Metadata-Version: 1.0
Name: doapfiend-ebuild
Version: 0.1.1
Summary: Doapfiend plugin. Create Gentoo Linux ebuild from DOAP.
Home-page: http://trac.doapspace.org/doapfiend/wiki/DfEbuild
Author: Rob Cakebread
Author-email: rob@doapspace.org
License: BSD-2
Keywords: doapfiend.plugin doap rdf ebuild gentoo doapfiend
Platform: UNKNOWN
Classifier: Development Status :: 2 - Pre-Alpha
Classifier: Intended Audience :: Developers
Classifier: Programming Language :: Python
Classifier: Topic :: Software Development :: Libraries :: Python Modules
